dtschema/.gitignore
dtschema/__init__.py
dtschema/check_compatible.py
dtschema/cmp_schema.py
dtschema/doc_validate.py
dtschema/dtb.py
dtschema/dtb2py.py
dtschema/dtb_validate.py
dtschema/extract_compatibles.py
dtschema/extract_example.py
dtschema/extract_props.py
dtschema/fixups.py
dtschema/lib.py
dtschema/mk_schema.py
dtschema/schema.py
dtschema/validator.py
dtschema/version.py
dtschema/meta-schemas/base.yaml
dtschema/meta-schemas/boolean.yaml
dtschema/meta-schemas/cell.yaml
dtschema/meta-schemas/clocks.yaml
dtschema/meta-schemas/core.yaml
dtschema/meta-schemas/dma.yaml
dtschema/meta-schemas/gpios.yaml
dtschema/meta-schemas/hwlock.yaml
dtschema/meta-schemas/iio.yaml
dtschema/meta-schemas/interrupts.yaml
dtschema/meta-schemas/iommu.yaml
dtschema/meta-schemas/items.yaml
dtschema/meta-schemas/keywords.yaml
dtschema/meta-schemas/mailbox.yaml
dtschema/meta-schemas/nodes.yaml
dtschema/meta-schemas/nvmem.yaml
dtschema/meta-schemas/phy.yaml
dtschema/meta-schemas/power-domain.yaml
dtschema/meta-schemas/pwm.yaml
dtschema/meta-schemas/reset.yaml
dtschema/meta-schemas/string-array.yaml
dtschema/meta-schemas/types.yaml
dtschema/meta-schemas/vendor-props.yaml
dtschema/schemas/aliases.yaml
dtschema/schemas/bootph.yaml
dtschema/schemas/cache-controller.yaml
dtschema/schemas/cache.yaml
dtschema/schemas/chosen.yaml
dtschema/schemas/cpu-map.yaml
dtschema/schemas/cpu.yaml
dtschema/schemas/cpus.yaml
dtschema/schemas/dt-core.yaml
dtschema/schemas/graph.yaml
dtschema/schemas/interconnects.yaml
dtschema/schemas/interrupt-controller.yaml
dtschema/schemas/interrupts.yaml
dtschema/schemas/memory.yaml
dtschema/schemas/msi-consumer.yaml
dtschema/schemas/numa-distance-map-v1.yaml
dtschema/schemas/options.yaml
dtschema/schemas/post-init-providers.yaml
dtschema/schemas/property-units.yaml
dtschema/schemas/reg.yaml
dtschema/schemas/root-node.yaml
dtschema/schemas/serial.yaml
dtschema/schemas/simple-bus.yaml
dtschema/schemas/system-idle-states.yaml
dtschema/schemas/types.yaml
dtschema-2025.8.dist-info/licenses/LICENSE.txt
dtschema-2025.8.dist-info/METADATA
dtschema-2025.8.dist-info/WHEEL
dtschema-2025.8.dist-info/entry_points.txt
dtschema-2025.8.dist-info/top_level.txt
dtschema-2025.8.dist-info/RECORD
