Metadata-Version: 2.4
Name: dtschema
Version: 2025.8
Summary: DeviceTree validation schema and tools
Author-email: Rob Herring <robh@kernel.org>
License: Copyright 2018-2019 Linaro Ltd.
Project-URL: Homepage, https://github.com/devicetree-org/dt-schema
Project-URL: Source, https://github.com/devicetree-org/dt-schema
Classifier: Programming Language :: Python :: 3
Classifier: License :: OSI Approved :: BSD License
Classifier: Operating System :: OS Independent
Classifier: Intended Audience :: Developers
Requires-Python: >=3.7
License-File: LICENSE.txt
Requires-Dist: ruamel.yaml>0.15.69
Requires-Dist: jsonschema<4.18,>=4.1.2
Requires-Dist: rfc3987
Requires-Dist: pylibfdt
Dynamic: license-file
